ollachat/__init__.py
ollachat/chatbot.py
ollachat/cli.py
ollachat-0.1.5.dist-info/LICENSE
ollachat-0.1.5.dist-info/METADATA
ollachat-0.1.5.dist-info/WHEEL
ollachat-0.1.5.dist-info/entry_points.txt
ollachat-0.1.5.dist-info/top_level.txt
ollachat-0.1.5.dist-info/RECORD
