Metadata-Version: 2.1
Name: ollachat
Version: 0.1.5
Summary: A Streamlit chatbot app integrating Ollama LLMs
Home-page: https://github.com/iamaziz/st_ollama
Author: Aziz Alto
Author-email: iamaziz.alto@gmail.com
Classifier: Programming Language :: Python :: 3
Classifier: License :: OSI Approved :: MIT License
Classifier: Operating System :: OS Independent
Requires-Python: >=3.6
License-File: LICENSE
Requires-Dist: streamlit
Requires-Dist: ollama
